ai_tools/Analyze_txt.py
ai_tools/Analyze_xml.py
ai_tools/IOU.py
ai_tools/Users\zhaomingming\AppData\Local\Continuum\anaconda2\lib\site-packages\ai_tools\draw.py
ai_tools/__init__.py
ai_tools/analysis_class.py
ai_tools/class2info.py
ai_tools/create_score_vector.py
ai_tools/darkchannel.py
ai_tools/dbop.py
ai_tools/draw.py
ai_tools/fileoperate.py
ai_tools/insert_image2db.py
ai_tools/luminance.py
ai_tools/main.py
ai_tools/microsoft_demo.py
ai_tools/photo_stiching.py
ai_tools/predict.py
ai_tools/read.py
ai_tools/roc.py
ai_tools/roc_matrix.py
ai_tools/roc_yolo.py
ai_tools/save2server.py
ai_tools/test_nms.py
ai_tools/txt2html.py
ai_tools/txt2xml.py
ai_tools/util.py
ai_tools/video2gif.py
ai_tools/video2img.py
ai_tools/wjdc.py
ai_tools/data/clf.pkl
ai_tools/data/wjdc_clf_800.pkl
ai_tools-0.3.9.dist-info/DESCRIPTION.rst
ai_tools-0.3.9.dist-info/METADATA
ai_tools-0.3.9.dist-info/RECORD
ai_tools-0.3.9.dist-info/WHEEL
ai_tools-0.3.9.dist-info/entry_points.txt
ai_tools-0.3.9.dist-info/metadata.json
ai_tools-0.3.9.dist-info/top_level.txt
package/__init__.py
