Metadata-Version: 2.0
Name: ai-tools
Version: 0.3.9
Summary: basic tools for ai
Home-page: http://www.zhaomingming.cn
Author: zhaomingming
Author-email: 13271929138@163.com
License: MIT
Platform: any
Provides-Extra: dev
Requires-Dist: check-manifest; extra == 'dev'
Provides-Extra: test
Requires-Dist: coverage; extra == 'test'
